python_pip/__init__.py
python_pip/commands.py
python_pip/pip.py
python_pip-1.1.dist-info/LICENSE
python_pip-1.1.dist-info/METADATA
python_pip-1.1.dist-info/WHEEL
python_pip-1.1.dist-info/top_level.txt
python_pip-1.1.dist-info/RECORD
