Metadata-Version: 2.1
Name: python-pip
Version: 1.1
Summary: Python PIP thin wrapper
Home-page: https://github.com/jpraychev/python-pip
Author: Jordan Raychev
Author-email: jpraychev@gmail.com
License: UNKNOWN
Project-URL: Bug Tracker, https://github.com/jpraychev/python-pip/issues
Platform: UNKNOWN
Classifier: Programming Language :: Python :: 3
Classifier: License :: OSI Approved :: MIT License
Classifier: Operating System :: OS Independent
Requires-Python: >=3.6
License-File: LICENSE
